python_multiprocess_crawler/__init__.py
python_multiprocess_crawler/main.py
python_multiprocess_crawler/main_test.py
python_multiprocess_crawler-1.6.4.dist-info/LICENSE
python_multiprocess_crawler-1.6.4.dist-info/METADATA
python_multiprocess_crawler-1.6.4.dist-info/WHEEL
python_multiprocess_crawler-1.6.4.dist-info/top_level.txt
python_multiprocess_crawler-1.6.4.dist-info/RECORD
