Metadata-Version: 2.1
Name: python-multiprocess-crawler
Version: 1.6.4
Summary: Python BaseClass for easier multiprocess web-crawling
Home-page: https://github.com/Kvintus/python_multiprocess_crawler
Author: Jákob Rolík
Author-email: rolik.jakob@gmail.com
License: UNKNOWN
Platform: UNKNOWN
Classifier: Programming Language :: Python :: 3
Classifier: License :: OSI Approved :: Artistic License
Classifier: Operating System :: OS Independent
Requires-Dist: requests
Requires-Dist: bs4
Requires-Dist: user-agent
